.coveragerc
CHANGES.rst
COPYRIGHT.txt
HACKING.rst
LICENSE.txt
README.rst
bootstrap.py
buildout.cfg
setup.py
doc/about.txt
doc/api.txt
doc/changes.txt
doc/conf.py
doc/index.txt
src/gocept/__init__.py
src/gocept.recordserialize.egg-info/PKG-INFO
src/gocept.recordserialize.egg-info/SOURCES.txt
src/gocept.recordserialize.egg-info/dependency_links.txt
src/gocept.recordserialize.egg-info/namespace_packages.txt
src/gocept.recordserialize.egg-info/not-zip-safe
src/gocept.recordserialize.egg-info/requires.txt
src/gocept.recordserialize.egg-info/top_level.txt
src/gocept/recordserialize/__init__.py
src/gocept/recordserialize/fixed.py
src/gocept/recordserialize/separated.py
src/gocept/recordserialize/tests/__init__.py
src/gocept/recordserialize/tests/test_doctest.py
src/gocept/recordserialize/tests/test_fixed.py
src/gocept/recordserialize/tests/test_separated.py