Metadata-Version: 1.1
Name: gocept.recordserialize
Version: 1.0
Summary: File writer/parser for fixed-width and character-separated files
Home-page: https://bitbucket.org/gocept/gocept.recordserialize/
Author: gocept <mail@gocept.com>
Author-email: mail@gocept.com
License: ZPL 2.1
Platform: UNKNOWN
Classifier: License :: OSI Approved :: Zope Public License
Classifier: Programming Language :: Python
Classifier: Programming Language :: Python :: 2
Classifier: Programming Language :: Python :: 2.7
Classifier: Programming Language :: Python :: 2 :: Only
